CBFV/__init__.py
CBFV/composition.py
CBFV/element_properties/jarvis.csv
CBFV/element_properties/magpie.csv
CBFV/element_properties/mat2vec.csv
CBFV/element_properties/oliynyk.csv
CBFV/element_properties/onehot.csv
CBFV/element_properties/random_200.csv
CBFV-1.1.0.dist-info/METADATA
CBFV-1.1.0.dist-info/WHEEL
CBFV-1.1.0.dist-info/top_level.txt
CBFV-1.1.0.dist-info/RECORD
